django_cron/__init__.py
django_cron/asgi.py
django_cron/settings.py
django_cron/urls.py
django_cron/wsgi.py
schedule_jobs/__init__.py
schedule_jobs/admin.py
schedule_jobs/apps.py
schedule_jobs/jobs.py
schedule_jobs/models.py
schedule_jobs/tests.py
schedule_jobs/views.py
schedule_jobs/migrations/__init__.py
django_ubuntu_cron-1.6.dist-info/METADATA
django_ubuntu_cron-1.6.dist-info/WHEEL
django_ubuntu_cron-1.6.dist-info/top_level.txt
django_ubuntu_cron-1.6.dist-info/RECORD
