Metadata-Version: 2.1
Name: django-ubuntu-cron
Version: 1.6
Summary: Create periodic or non periodic task using ubuntu crontab in your django project
Home-page: https://github.com/kumar-sanchay/django-ubuntu-cron
Author: Sanchay Kumar
Author-email: dsanchaykumar@gmail.com
License: MIT
Platform: UNKNOWN
